LICENSE
README.md
setup.py
automationfx/__init__.py
automationfx/__main__.py
automationfx/auth.py
automationfx/settings.py
automationfx.egg-info/PKG-INFO
automationfx.egg-info/SOURCES.txt
automationfx.egg-info/dependency_links.txt
automationfx.egg-info/entry_points.txt
automationfx.egg-info/not-zip-safe
automationfx.egg-info/requires.txt
automationfx.egg-info/top_level.txt
automationfx/actions/__init__.py
automationfx/api/__init__.py
automationfx/api/client.py
automationfx/models/__init__.py
automationfx/models/phones.py