Metadata-Version: 2.1
Name: automationfx
Version: 0.1.2201
Summary: AutomationFX SDK for Cisco Unified Communication Manager
Home-page: https://github.com/unifiedfx/automationfx-python
Author: Stephen Welsh
Author-email: support@unifiedfx.com
License: MIT
Download-URL: https://github.com/unifiedfx/automationfx-python/archive/0.1.tar.gz
Keywords: Cisco Phone Automation
Platform: UNKNOWN
Classifier: Development Status :: 3 - Alpha
Classifier: License :: OSI Approved :: MIT License
Classifier: Programming Language :: Python :: 2.7
License-File: LICENSE
